ipytopy/__init__.py
ipytopy/ipytopy.py
ipytopy-0.0.3.dist-info/METADATA
ipytopy-0.0.3.dist-info/WHEEL
ipytopy-0.0.3.dist-info/top_level.txt
ipytopy-0.0.3.dist-info/RECORD
