Metadata-Version: 2.1
Name: ipytopy
Version: 0.0.3
Requires-Dist: logclshelper
Requires-Dist: syshelper
